{
  "id": "indo_scythian_kingdom",
  "name": "Indo-Scythian Kingdom",
  "ruling_ethnicity": "scythian",
  "cultural_language": "prakrit_dialects",
  "ideology": {
    "religion": "buddhism",
    "government": "monarchy"
  },
  "territories": [
    "indus_valley",
    "punjab"
  ],
  "start": -200,
  "end": 400,
  "note": "Saka (Scythian) rulers who displaced the Indo-Greeks. The Western Satraps and Northern Satraps were the major branches. Patronised Buddhism and used Greek-derived scripts. Azes I established the Azes era (c.47 BCE) used in dating."
}
