{
  "id": "bulgaria",
  "title": "History of Bulgaria",
  "columns": [
    {
      "id": "era",
      "name": "Era",
      "slots": 1,
      "type": "era"
    },
    {
      "id": "north",
      "name": "N. Bulgaria / Moesia",
      "slots": 1
    },
    {
      "id": "cent",
      "name": "C. Bulgaria (Tărnovo · Sofia)",
      "slots": 1
    },
    {
      "id": "south",
      "name": "S. Bulgaria / Thrace",
      "slots": 1
    }
  ],
  "rows": [
    {
      "era": {
        "label": "Ancient",
        "rowspan": 3
      },
      "cells": [
        {
          "stack": [
            {
              "label": "Getae · Triballi",
              "note": "Thracian tribes, Danubian plain",
              "polity": "getae_triballi"
            }
          ],
          "span": 1
        },
        {
          "stack": [
            {
              "label": "Thracian tribes",
              "polity": "thracian_tribes"
            }
          ],
          "span": 1
        },
        {
          "stack": [
            {
              "label": "Odrysian Kingdom",
              "note": "c.480–170 BCE — Thrace core",
              "polity": "odrysian_kingdom"
            },
            {
              "label": "Achaemenid Persian Empire",
              "note": "513–479 BCE",
              "polity": "achaemenid_persian_empire"
            }
          ],
          "span": 1
        }
      ]
    },
    {
      "era": null,
      "cells": [
        {
          "stack": [
            {
              "label": "Macedonian Kingdom — Philip II (Triballi, 339 BCE)",
              "polity": "macedonian_kingdom"
            },
            {
              "label": "Lysimachus — Kingdom of Thrace",
              "note": "305–281 BCE",
              "polity": "lysimachus"
            },
            {
              "label": "Odrysian revival (Roman client)",
              "note": "3rd–1st c. BCE",
              "polity": "odrysian_revival"
            }
          ],
          "span": 1
        },
        {
          "stack": [
            {
              "label": "Macedonian Kingdom",
              "polity": "macedonian_kingdom"
            },
            {
              "label": "Lysimachus · Seleucid (brief)",
              "polity": "lysimachus_seleucid"
            },
            {
              "label": "Odrysian client",
              "polity": "odrysian_client"
            }
          ],
          "span": 1
        },
        {
          "stack": [
            {
              "label": "Macedonian Kingdom",
              "polity": "macedonian_kingdom"
            },
            {
              "label": "Lysimachus · Seleucid",
              "polity": "lysimachus_seleucid"
            },
            {
              "label": "Odrysian revival — client of Rome",
              "polity": "odrysian_revival"
            }
          ],
          "span": 1
        }
      ]
    },
    {
      "era": null,
      "cells": [
        {
          "stack": [
            {
              "label": "Roman Moesia province",
              "note": "c.6 CE–",
              "polity": "roman_moesia_province"
            },
            {
              "label": "Gothic raids · settlement",
              "note": "3rd–4th c.",
              "polity": "gothic_raids"
            },
            {
              "label": "Hunnic raids",
              "note": "4th–5th c.",
              "polity": "hunnic_raids"
            }
          ],
          "span": 1
        },
        {
          "stack": [
            {
              "label": "Roman",
              "polity": "roman_empire"
            },
            {
              "label": "Gothic · Hunnic raids",
              "polity": "gothic_hunnic_raids"
            }
          ],
          "span": 1
        },
        {
          "stack": [
            {
              "label": "Roman Thrace province",
              "note": "46 CE–",
              "polity": "roman_thrace_province"
            },
            {
              "label": "Byzantine (Eastern Roman)",
              "note": "from 395 CE",
              "polity": "byzantine_empire"
            }
          ],
          "span": 1
        }
      ]
    },
    {
      "era": {
        "label": "Medieval",
        "rowspan": 4
      },
      "cells": [
        {
          "stack": [
            {
              "label": "Bulgar Khanate — Asparuh · Tervel",
              "note": "681–",
              "polity": "bulgar_khanate"
            },
            {
              "label": "Pliska (first capital)",
              "polity": "pliska"
            }
          ],
          "span": 1
        },
        {
          "stack": [
            {
              "label": "Byzantine Empire",
              "polity": "byzantine_empire"
            },
            {
              "label": "South Slavic migration settling",
              "polity": "south_slavic_migration_settling"
            }
          ],
          "span": 1
        },
        {
          "stack": [
            {
              "label": "Byzantine Empire — Thrace (core territory)",
              "polity": "byzantine_empire"
            }
          ],
          "span": 1
        }
      ]
    },
    {
      "era": null,
      "cells": [
        {
          "stack": [
            {
              "label": "First Bulgarian Empire — Krum · Boris I · Simeon I",
              "note": "803–1018",
              "polity": "first_bulgarian_empire"
            },
            {
              "label": "Pliska → Preslav (capitals)"
            }
          ],
          "span": 2
        },
        {
          "stack": [
            {
              "label": "Byzantine Empire — Thrace",
              "polity": "byzantine_empire"
            },
            {
              "label": "Bulgarian border pressure",
              "polity": "bulgarian_border_pressure"
            }
          ],
          "span": 1
        }
      ]
    },
    {
      "era": null,
      "cells": [
        {
          "stack": [
            {
              "label": "Byzantine reconquest — Basil II",
              "note": "1018",
              "polity": "byzantine_reconquest"
            },
            {
              "label": "Second Bulgarian Empire — Tărnovo",
              "note": "1185–1396",
              "polity": "second_bulgarian_empire"
            }
          ],
          "span": 2
        },
        {
          "stack": [
            {
              "label": "Byzantine Empire — Thrace",
              "polity": "byzantine_empire"
            },
            {
              "label": "Bulgarian–Byzantine contested",
              "polity": "bulgarian_byzantine_contested"
            }
          ],
          "span": 1
        }
      ]
    },
    {
      "era": null,
      "cells": [
        {
          "stack": [
            {
              "label": "Ottoman conquest",
              "note": "Tărnovo 1393 · Vidin 1396"
            }
          ],
          "span": 3
        }
      ]
    },
    {
      "era": {
        "label": "Ottoman",
        "rowspan": 1
      },
      "cells": [
        {
          "polity": "ottoman_empire",
          "label": "Ottoman Empire — Danube vilayet · Rumelia · Bulgarian national revival movement",
          "span": 3
        }
      ]
    },
    {
      "era": {
        "label": "Modern",
        "rowspan": 4
      },
      "cells": [
        {
          "stack": [
            {
              "label": "Principality of Bulgaria",
              "note": "1878–1908",
              "polity": "principality_of_bulgaria"
            },
            {
              "label": "Treaty of San Stefano · Congress of Berlin · Russian protectorate"
            }
          ],
          "span": 3
        }
      ]
    },
    {
      "era": null,
      "cells": [
        {
          "stack": [
            {
              "label": "Kingdom of Bulgaria",
              "note": "1908–1946",
              "polity": "kingdom_of_bulgaria"
            },
            {
              "label": "Balkan Wars 1912–13 · WWI (Central Powers) · WWII (Axis-aligned)"
            }
          ],
          "span": 3
        }
      ]
    },
    {
      "era": null,
      "cells": [
        {
          "stack": [
            {
              "label": "People's Republic of Bulgaria",
              "note": "1946–1990",
              "polity": "peoples_republic_of_bulgaria"
            },
            {
              "label": "Soviet-aligned · Warsaw Pact"
            }
          ],
          "span": 3
        }
      ]
    },
    {
      "era": null,
      "cells": [
        {
          "label": "Republic of Bulgaria — NATO (2004) · EU member (2007)",
          "span": 3
        }
      ]
    }
  ],
  "footnotes": [
    "Odrysian Kingdom: The first major Thracian state, centred in southern Thrace (modern southern Bulgaria and northern Turkey/Greece); became a Roman client kingdom.",
    "Bulgar Khanate (681 CE): Founded after the Bulgars under Asparuh crossed the Danube; recognised by Byzantine treaty; converted to Christianity under Boris I (864 CE).",
    "Second Bulgarian Empire: Re-established by the Asen brothers (Peter and Asen) in 1185 after a revolt against Byzantium; peaked under Ivan Asen II (1218–1241).",
    "Principality of Bulgaria: Created by Treaty of San Stefano (1878) after the Russo-Turkish War; scope reduced by Congress of Berlin; full independence declared 1908.",
    "WWII: Bulgaria was Axis-aligned but did not declare war on the USSR; after Soviet entry in 1944, a communist-led Fatherland Front seized power."
  ]
}
